HamTool/__init__.py
HamTool/band_cal.yaml
HamTool/band_cal_parallel.py
HamTool/band_cal_parallel_soc.py
band_cal_parallel_soc/__init__.py
band_cal_parallel_soc/band_cal.yaml
band_cal_parallel_soc/band_cal_parallel_soc.py
band_cal_parallel-0.1.12.dist-info/METADATA
band_cal_parallel-0.1.12.dist-info/WHEEL
band_cal_parallel-0.1.12.dist-info/entry_points.txt
band_cal_parallel-0.1.12.dist-info/top_level.txt
band_cal_parallel-0.1.12.dist-info/RECORD
