Metadata-Version: 2.1
Name: band-cal-parallel
Version: 0.1.12
Summary: HamGNN tool
Download-URL: 
Author: Yang Zhong
License: MIT
Platform: UNKNOWN
Requires-Python: >=3.9
Requires-Dist: numpy
Requires-Dist: torch
Requires-Dist: torch-geometric
Requires-Dist: pymatgen
Requires-Dist: mpitool
